context_logging/__init__.py
context_logging/config.py
context_logging/context.py
context_logging/log_record.py
context_logging/logger.py
context_logging/utils.py
context_logging-1.2.0.dist-info/LICENSE
context_logging-1.2.0.dist-info/METADATA
context_logging-1.2.0.dist-info/WHEEL
context_logging-1.2.0.dist-info/RECORD
