Metadata-Version: 2.1
Name: context_logging
Version: 1.2.0
Summary: Tool for easy logging with current context information
Home-page: https://pypi.org/project/context_logging
License: MIT
Keywords: logging,logger,context
Author: Evgeniy Afonasev
Author-email: ea.afonasev@gmail.com
Requires-Python: >=3.7,<4.0
Classifier: License :: OSI Approved :: MIT License
Classifier: Programming Language :: Python :: 3
Classifier: Programming Language :: Python :: 3.7
Classifier: Programming Language :: Python :: 3.8
Classifier: Programming Language :: Python :: 3.9
Classifier: Programming Language :: Python :: 3.10
Classifier: Programming Language :: Python :: 3.11
Requires-Dist: contextvars_executor (>=0.0.1,<0.0.2)
Requires-Dist: deprecated (>=1.2.10,<2.0.0)
Project-URL: Repository, https://github.com/Afonasev/context_logging
